README.md
setup.py
feishu/__init__.py
feishu/__version__.py
feishu.egg-info/PKG-INFO
feishu.egg-info/SOURCES.txt
feishu.egg-info/dependency_links.txt
feishu.egg-info/requires.txt
feishu.egg-info/top_level.txt