Metadata-Version: 2.1
Name: feishu
Version: 0.0.1
Summary: python sdk for lark and feishu ( open.feishu.cn )
Home-page: https://github.com/larksuite/feishu
Author: chyroc
Author-email: chyroc@bytedance.com
License: UNKNOWN
Keywords: lark
Platform: UNKNOWN
Classifier: Intended Audience :: Developers
Classifier: Programming Language :: Python :: 2.7
Classifier: Programming Language :: Python :: 3.6
Classifier: Programming Language :: Python :: 3.7
Requires-Python: >=2.7,!=3.0.*,!=3.1.*,!=3.2.*,!=3.3.*,!=3.4.*,!=3.5.*
Provides-Extra: dev
